bidoc/__init__.py
bidoc/__main__.py
bidoc/__version__.py
bidoc/ai_summary.py
bidoc/cli.py
bidoc/config.py
bidoc/constants.py
bidoc/dax_formatter.py
bidoc/json_generator.py
bidoc/logger.py
bidoc/markdown_generator.py
bidoc/metadata_schemas.py
bidoc/pbix_parser.py
bidoc/summary_strategies.py
bidoc/tableau_parser.py
bidoc/test_data.py
bidoc/utils.py
bidoc-1.0.0.dist-info/licenses/LICENSE
bidoc-1.0.0.dist-info/METADATA
bidoc-1.0.0.dist-info/WHEEL
bidoc-1.0.0.dist-info/entry_points.txt
bidoc-1.0.0.dist-info/top_level.txt
bidoc-1.0.0.dist-info/RECORD
