Metadata-Version: 2.4
Name: bidoc
Version: 1.0.0
Summary: Business Intelligence documentation tool for Power BI and Tableau
Author: BI Documentation Tool Team
Maintainer: BI Documentation Tool Team
License: Business Source License 1.1
Project-URL: Homepage, https://github.com/your-org/bi-doc
Project-URL: Documentation, https://github.com/your-org/bi-doc#readme
Project-URL: Repository, https://github.com/your-org/bi-doc
Project-URL: Bug Tracker, https://github.com/your-org/bi-doc/issues
Project-URL: Changelog, https://github.com/your-org/bi-doc/blob/main/CHANGELOG.md
Project-URL: Integration Guide, https://github.com/your-org/bi-doc/blob/main/INTEGRATION_HOOKS.md
Keywords: power-bi,tableau,business-intelligence,documentation,metadata,data-catalog,enterprise-integration
Classifier: Development Status :: 5 - Production/Stable
Classifier: Intended Audience :: Developers
Classifier: Intended Audience :: System Administrators
Classifier: Intended Audience :: Information Technology
Classifier: License :: Other/Proprietary License
Classifier: Operating System :: OS Independent
Classifier: Programming Language :: Python :: 3
Classifier: Programming Language :: Python :: 3.8
Classifier: Programming Language :: Python :: 3.9
Classifier: Programming Language :: Python :: 3.10
Classifier: Programming Language :: Python :: 3.11
Classifier: Programming Language :: Python :: 3.12
Classifier: Topic :: Documentation
Classifier: Topic :: Office/Business
Classifier: Topic :: Software Development :: Documentation
Classifier: Topic :: System :: Archiving
Classifier: Topic :: Utilities
Requires-Python: >=3.8
License-File: LICENSE
Requires-Dist: pbixray>=0.3.3
Requires-Dist: tableaudocumentapi>=0.11
Requires-Dist: click>=8.0.0
Requires-Dist: jinja2>=3.1.0
Requires-Dist: pandas>=1.5.0
Requires-Dist: lxml>=4.9.0
Requires-Dist: colorama>=0.4.0
Requires-Dist: toml>=0.10.2
Provides-Extra: dev
Requires-Dist: pytest>=7.0.0; extra == "dev"
Requires-Dist: pytest-cov>=4.0.0; extra == "dev"
Requires-Dist: black>=23.0.0; extra == "dev"
Requires-Dist: ruff>=0.1.0; extra == "dev"
Requires-Dist: mypy>=1.0.0; extra == "dev"
Requires-Dist: bandit>=1.7.0; extra == "dev"
Requires-Dist: pre-commit>=3.0.0; extra == "dev"
Requires-Dist: sphinx>=6.0.0; extra == "dev"
Requires-Dist: sphinx-rtd-theme>=1.3.0; extra == "dev"
Requires-Dist: jupyter>=1.0.0; extra == "dev"
Provides-Extra: docs
Requires-Dist: sphinx>=6.0.0; extra == "docs"
Requires-Dist: sphinx-rtd-theme>=1.3.0; extra == "docs"
Requires-Dist: myst-parser>=2.0.0; extra == "docs"
Requires-Dist: sphinx-click>=4.4.0; extra == "docs"
Provides-Extra: test
Requires-Dist: pytest>=7.0.0; extra == "test"
Requires-Dist: pytest-cov>=4.0.0; extra == "test"
Requires-Dist: pytest-mock>=3.10.0; extra == "test"
Dynamic: license-file
Dynamic: requires-python
